.svnignore
README.txt
bootstrap.py
buildout-plone3.cfg
setup.cfg
setup.py
docs/CHANGES.txt
docs/CONTRIBUTORS.txt
docs/INSTALL.txt
docs/LICENSE.GPL
docs/LICENSE.txt
src/slc/__init__.py
src/slc.cleanwordpastedtext.egg-info/PKG-INFO
src/slc.cleanwordpastedtext.egg-info/SOURCES.txt
src/slc.cleanwordpastedtext.egg-info/dependency_links.txt
src/slc.cleanwordpastedtext.egg-info/entry_points.txt
src/slc.cleanwordpastedtext.egg-info/namespace_packages.txt
src/slc.cleanwordpastedtext.egg-info/not-zip-safe
src/slc.cleanwordpastedtext.egg-info/requires.txt
src/slc.cleanwordpastedtext.egg-info/top_level.txt
src/slc/cleanwordpastedtext/__init__.py
src/slc/cleanwordpastedtext/configure.zcml
src/slc/cleanwordpastedtext/events.py
src/slc/cleanwordpastedtext/example_text.txt
src/slc/cleanwordpastedtext/schemaextender.py
src/slc/cleanwordpastedtext/tests.py
src/slc/cleanwordpastedtext/utils.py
src/slc/cleanwordpastedtext/Extensions/cleanWordPastedText.py