Metadata-Version: 1.0
Name: slc.cleanwordpastedtext
Version: 1.2.8
Summary: Clean up the HTML formatting problems introduced by pasting content from MSWord into Plone's RichText fields.
Home-page: http://svn.plone.org/svn/plone/plone.example
Author: Syslab.com GmbH
Author-email: info@syslab.com
License: GPL
Keywords: plone syslab simplon microsoft word
Platform: UNKNOWN
Classifier: Framework :: Plone
Classifier: Programming Language :: Python
Classifier: Topic :: Software Development :: Libraries :: Python Modules
